ftww1.py
ftww-0.0.0.8.dist-info/METADATA
ftww-0.0.0.8.dist-info/WHEEL
ftww-0.0.0.8.dist-info/top_level.txt
ftww-0.0.0.8.dist-info/RECORD
